README.md
setup.py
unicodeblock/__init__.py
unicodeblock/blocks.py
unicodeblock/lower.py
unicodeblock/sequence.py
unicodeblock.egg-info/PKG-INFO
unicodeblock.egg-info/SOURCES.txt
unicodeblock.egg-info/dependency_links.txt
unicodeblock.egg-info/not-zip-safe
unicodeblock.egg-info/top_level.txt