Metadata-Version: 1.0
Name: unicodeblock
Version: 0.3.1
Summary: Python Unicode Block Utilities
Home-page: https://github.com/neuront/pyunicodeblock
Author: Neuron Teckid
Author-email: lene13@gmail.com
License: MIT
Keywords: Python UnicodeBlock
Platform: UNKNOWN
